balerin/__init__.py
balerin/common/__init__.py
balerin/common/exceptions.py
balerin/common/mixin.py
balerin/common/structs.py
balerin/common/utils.py
balerin/packaging/__init__.py
balerin/packaging/base.py
balerin/packaging/exceptions.py
balerin/packaging/hooks.py
balerin/packaging/manager.py
balerin-0.1.4.dist-info/LICENSE
balerin-0.1.4.dist-info/METADATA
balerin-0.1.4.dist-info/WHEEL
balerin-0.1.4.dist-info/top_level.txt
balerin-0.1.4.dist-info/RECORD
