Metadata-Version: 2.1
Name: balerin
Version: 0.1.4
Summary: A python package startup orchestrator. it can handle loading all packages of an application at startup time respecting package dependencies.
Home-page: https://github.com/mononobi/balerin
Author: Mohamad Nobakht
Author-email: mohamadnobakht@gmail.com
Maintainer: Mohamad Nobakht
Maintainer-email: mohamadnobakht@gmail.com
License: BSD-3-Clause
Project-URL: Code, https://github.com/mononobi/balerin
Project-URL: Issue tracker, https://github.com/mononobi/balerin/issues
Keywords: python balerin package-manager packaging startup auto-importstartup-import syntax-error package-loader
Platform: UNKNOWN
Classifier: Development Status :: 5 - Production/Stable
Classifier: Intended Audience :: Developers
Classifier: License :: OSI Approved :: BSD License
Classifier: Operating System :: OS Independent
Classifier: Programming Language :: Python
Classifier: Programming Language :: Python :: 3.6
Classifier: Programming Language :: Python :: 3.7
Classifier: Programming Language :: Python :: 3.8
Classifier: Programming Language :: Python :: 3.9
Classifier: Programming Language :: Python :: 3.10
Classifier: Programming Language :: Python :: Implementation :: CPython
Classifier: Topic :: Software Development :: Libraries :: Python Modules
Requires-Python: >=3.6
License-File: LICENSE
